inco_32/__init__.py
inco_32/errinco.py
inco_32/inco_32.py
inco_32-4.4.1.dist-info/LICENSE.txt
inco_32-4.4.1.dist-info/METADATA
inco_32-4.4.1.dist-info/WHEEL
inco_32-4.4.1.dist-info/top_level.txt
inco_32-4.4.1.dist-info/RECORD
